napari_text_layer/__init__.py
napari_text_layer/textlayer.py
napari_text_layer-0.1.2.dist-info/LICENSE
napari_text_layer-0.1.2.dist-info/METADATA
napari_text_layer-0.1.2.dist-info/WHEEL
napari_text_layer-0.1.2.dist-info/entry_points.txt
napari_text_layer-0.1.2.dist-info/top_level.txt
napari_text_layer-0.1.2.dist-info/RECORD
