Metadata-Version: 2.1
Name: napari-text-layer
Version: 0.1.2
Summary: Text layer for bio-image annotation.
Home-page: UNKNOWN
Author: Hanjin Liu
Author-email: liuhanjin-sc@g.ecc.u-tokyo.ac.jp
License: BSD 3-Clause
Download-URL: https://github.com/hanjinliu/napari-text-layer
Platform: UNKNOWN
Classifier: Framework :: napari
Classifier: Programming Language :: Python
Classifier: Programming Language :: Python :: 3
Classifier: Programming Language :: Python :: 3.7
Classifier: Programming Language :: Python :: 3.8
Classifier: Programming Language :: Python :: 3.9
Requires-Python: >=3.7
License-File: LICENSE
